Workbook

Sheet Resumen
A1: Base de datos de productos colombianos · Logística y trivia
A2: Datos referenciales/ilustrativos (precios, pesos, rutas, vida útil) pensados para un juego de tarjetas de trivia. Verifica los valores antes de usarlos como información comercial real.
A4: Indicadores | B4: Valor | D4: Cómo usar este archivo
A5: Productos registrados | B5: =COUNTA(Productos!A:A)-1 -> 30 | D5: • Productos: ficha de cada producto (SKU, marca, medida, referencia, conservación, tipo, tamaño, origen), como en la tarjeta de ejemplo.
A6: Tiendas registradas | B6: =COUNTA(Tiendas!A:A)-1 -> 11 | D6: • Logística: pesos, cajas, estibas, temperatura, vida útil, vehículo y ruta. Columnas con encabezado morado = fórmulas (no editar).
A7: Registros de inventario | B7: =COUNTA(Inventario!A:A)-1 -> 90 | D7: • Tiendas: cadenas y formatos, CD que las abastece, frecuencia de reabastecimiento y si tienen cuarto frío.
A8: Registros por reabastecer | B8: =COUNTIF(Inventario!J:J,"Reabastecer") -> 27 | D8: • Inventario: precio, stock y mínimo por tienda y producto. El estado y el valor se calculan solos.
A9: Valor total del inventario (COP) | B9: =SUM(Inventario!K:K) -> 125434800 | D9: • Trivia: afirmaciones Verdadero/Falso con explicación, dificultad, puntos y SKU relacionado. Listas para importar a tu sistema de tarjetas.
A10: Productos con transporte controlado | B10: =COUNTIF(Logística!J:J,"Sí") -> 12 | D10: • Encabezado azul oscuro = datos que puedes editar. Encabezado morado = calculado por fórmula.
A11: Total de afirmaciones de trivia | B11: =COUNTA(Trivia!A:A)-1 -> 166 | D11: • Las afirmaciones de trivia son texto fijo creado a partir de estos datos: si cambias un dato, actualiza la afirmación que lo usa (ver columna «Fuente del dato»).
A12: Verdaderas | B12: =COUNTIF(Trivia!D:D,"Verdadero") -> 85 | D12: • Para sacar una tarjeta: usa 'Afirmación' como frente y 'Respuesta correcta' + 'Explicación' como reverso. Filtra por 'Activa' = Sí.
A13: Falsas | B13: =COUNTIF(Trivia!D:D,"Falso") -> 81
A15: Afirmaciones por tema | B15: Cantidad
A16: Cadena de frío | B16: =COUNTIF(Trivia!B:B,A16) -> 30
A17: Paletizado y embalaje | B17: =COUNTIF(Trivia!B:B,A17) -> 30
A18: Vida útil y rotación | B18: =COUNTIF(Trivia!B:B,A18) -> 8
A19: Transporte y rutas | B19: =COUNTIF(Trivia!B:B,A19) -> 15
A20: Origen y producto | B20: =COUNTIF(Trivia!B:B,A20) -> 37
A21: Inventario en tienda | B21: =COUNTIF(Trivia!B:B,A21) -> 26
A22: Conceptos de logística | B22: =COUNTIF(Trivia!B:B,A22) -> 20
A24: Afirmaciones por dificultad | B24: Cantidad
A25: Fácil | B25: =COUNTIF(Trivia!F:F,A25) -> 82
A26: Media | B26: =COUNTIF(Trivia!F:F,A26) -> 52
A27: Difícil | B27: =COUNTIF(Trivia!F:F,A27) -> 32

Sheet Productos
A1: SKU | B1: Producto | C1: Categoría | D1: Subcategoría | E1: Descripción | F1: Marca | G1: Medida | H1: Referencia | I1: Conservación | J1: Qué tipo es | K1: Tamaño | L1: Origen (dpto.) | M1: Emoji
A2: 00219 | B2: Banano premium | C2: Frutas y verduras | D2: Frescos | E2: Banano fresco seleccionado, fuente natural de energía. | F2: Frescura | G2: 1 kg | H2: FRU-BA-001 | I2: Temperatura ambiente | J2: Fruta fresca | K2: 1 kg | L2: Antioquia (Urabá) | M2: 🍌
A3: 00220 | B3: Aguacate Hass | C3: Frutas y verduras | D3: Frescos | E3: Aguacate Hass de pulpa cremosa, cosecha nacional. | F3: Frescura | G3: 1 kg | H3: FRU-AG-002 | I3: Temperatura ambiente | J3: Fruta fresca | K3: Bolsa 1 kg | L3: Antioquia | M3: 🥑
A4: 00221 | B4: Papa criolla lavada | C4: Frutas y verduras | D4: Tubérculos | E4: Papa criolla amarilla lavada, lista para cocinar. | F4: Frescura | G4: 500 g | H4: FRU-PC-003 | I4: Lugar fresco y seco | J4: Tubérculo | K4: Bolsa 500 g | L4: Cundinamarca | M4: 🥔
A5: 00222 | B5: Plátano hartón | C5: Frutas y verduras | D5: Frescos | E5: Plátano hartón verde, ideal para patacones y sancocho. | F5: Frescura | G5: 1 kg | H5: FRU-PL-004 | I5: Temperatura ambiente | J5: Fruta fresca | K5: 1 kg | L5: Quindío | M5: 🍌
A6: 00223 | B6: Uchuva con capacho | C6: Frutas y verduras | D6: Frescos | E6: Uchuva fresca con capacho, dulce y ligeramente ácida. | F6: Frescura | G6: 250 g | H6: FRU-UC-005 | I6: Refrigerado 2–6 °C | J6: Fruta fresca | K6: Canastilla 250 g | L6: Cundinamarca | M6: 🟠
A7: 00224 | B7: Lulo | C7: Frutas y verduras | D7: Frescos | E7: Lulo fresco, base de los jugos más típicos de Colombia. | F7: Frescura | G7: 500 g | H7: FRU-LU-006 | I7: Refrigerado 7–10 °C | J7: Fruta fresca | K7: Bolsa 500 g | L7: Huila | M7: 🍊
A8: 00225 | B8: Mango Tommy | C8: Frutas y verduras | D8: Frescos | E8: Mango Tommy de pulpa firme y dulce. | F8: Frescura | G8: 1 kg | H8: FRU-MA-007 | I8: Temperatura ambiente | J8: Fruta fresca | K8: 1 kg | L8: Tolima | M8: 🥭
A9: 00226 | B9: Cebolla cabezona blanca | C9: Frutas y verduras | D9: Hortalizas | E9: Cebolla cabezona blanca seleccionada. | F9: Frescura | G9: 1 kg | H9: FRU-CE-008 | I9: Lugar fresco y seco | J9: Hortaliza | K9: Malla 1 kg | L9: Boyacá | M9: 🧅
A10: 00227 | B10: Leche entera pasteurizada | C10: Lácteos y refrigerados | D10: Leches | E10: Leche entera pasteurizada en bolsa. | F10: Colanta | G10: 1 L | H10: LAC-LE-009 | I10: Refrigerado 2–6 °C | J10: Lácteo | K10: Bolsa 1 L | L10: Antioquia | M10: 🥛
A11: 00228 | B11: Yogurt entero | C11: Lácteos y refrigerados | D11: Yogures | E11: Yogurt entero cremoso. | F11: Alpina | G11: 1 L | H11: LAC-YO-010 | I11: Refrigerado 2–6 °C | J11: Lácteo | K11: Bolsa 1 L | L11: Cundinamarca | M11: 🥛
A12: 00229 | B12: Queso campesino | C12: Lácteos y refrigerados | D12: Quesos | E12: Queso campesino fresco, suave y de sabor lácteo. | F12: Colanta | G12: 500 g | H12: LAC-QU-011 | I12: Refrigerado 2–6 °C | J12: Lácteo | K12: Bloque 500 g | L12: Antioquia | M12: 🧀
... A31: 00248 | B31: Papel higiénico | C31: Hogar y aseo | D31: Aseo personal | E31: Papel higiénico de doble hoja. | F31: Familia | G31: 12 rollos | H31: HOG-PH-030 | I31: Lugar fresco y seco | J31: Papel higiénico | K31: Paquete x 12 | L31: Antioquia | M31: 🧻

Sheet Logística
A1: SKU | B1: Producto | C1: Peso unitario (kg) | D1: Unidades por caja | E1: Peso por caja (kg) | F1: Cajas por estiba | G1: Unidades por estiba | H1: Peso neto por estiba (kg) | I1: Embalaje | J1: Transporte con temp. controlada | K1: Temp. mín (°C) | L1: Temp. máx (°C) | M1: Vida útil (días) | N1: Vehículo típico | O1: Origen de despacho | P1: CD destino | Q1: Distancia aprox. (km) | R1: Tránsito aprox. (h) | S1: Máx. niveles apilables
A2: 00219 | B2: =IFERROR(INDEX(Productos!$B:$B,MATCH($A2,Productos!$A:$A,0)),"") -> Banano premium | C2: 1 | D2: 18 | E2: =C2*D2 -> 18 | F2: 48 | G2: =D2*F2 -> 864 | H2: =E2*F2 -> 864 | I2: Caja de cartón ventilada | J2: Sí | K2: 13 | L2: 15 | M2: 7 | N2: Tractomula refrigerada | O2: Apartadó | P2: CD Medellín | Q2: 310 | R2: 7 | S2: 5
A3: 00220 | B3: =IFERROR(INDEX(Productos!$B:$B,MATCH($A3,Productos!$A:$A,0)),"") -> Aguacate Hass | C3: 1 | D3: 10 | E3: =C3*D3 -> 10 | F3: 64 | G3: =D3*F3 -> 640 | H3: =E3*F3 -> 640 | I3: Caja de cartón ventilada | J3: Sí | K3: 5 | L3: 8 | M3: 10 | N3: Camión refrigerado | O3: Jardín | P3: CD Medellín | Q3: 130 | R3: 3.5 | S3: 6
A4: 00221 | B4: =IFERROR(INDEX(Productos!$B:$B,MATCH($A4,Productos!$A:$A,0)),"") -> Papa criolla lavada | C4: 0.5 | D4: 20 | E4: =C4*D4 -> 10 | F4: 60 | G4: =D4*F4 -> 1200 | H4: =E4*F4 -> 600 | I4: Caja plástica | J4: Sí | K4: 8 | L4: 12 | M4: 20 | N4: Furgón seco | O4: Zipaquirá | P4: CD Bogotá | Q4: 60 | R4: 2 | S4: 5
A5: 00222 | B5: =IFERROR(INDEX(Productos!$B:$B,MATCH($A5,Productos!$A:$A,0)),"") -> Plátano hartón | C5: 1 | D5: 15 | E5: =C5*D5 -> 15 | F5: 40 | G5: =D5*F5 -> 600 | H5: =E5*F5 -> 600 | I5: Caja de cartón ventilada | J5: Sí | K5: 13 | L5: 15 | M5: 10 | N5: Camión refrigerado | O5: Armenia | P5: CD Cali | Q5: 190 | R5: 4 | S5: 5
A6: 00223 | B6: =IFERROR(INDEX(Productos!$B:$B,MATCH($A6,Productos!$A:$A,0)),"") -> Uchuva con capacho | C6: 0.25 | D6: 12 | E6: =C6*D6 -> 3 | F6: 120 | G6: =D6*F6 -> 1440 | H6: =E6*F6 -> 360 | I6: Canastilla plástica | J6: Sí | K6: 2 | L6: 6 | M6: 15 | N6: Camión refrigerado | O6: Fusagasugá | P6: CD Bogotá | Q6: 65 | R6: 2.5 | S6: 4
A7: 00224 | B7: =IFERROR(INDEX(Productos!$B:$B,MATCH($A7,Productos!$A:$A,0)),"") -> Lulo | C7: 0.5 | D7: 12 | E7: =C7*D7 -> 6 | F7: 100 | G7: =D7*F7 -> 1200 | H7: =E7*F7 -> 600 | I7: Caja de cartón ventilada | J7: Sí | K7: 7 | L7: 10 | M7: 12 | N7: Camión refrigerado | O7: Neiva | P7: CD Bogotá | Q7: 310 | R7: 7 | S7: 5
A8: 00225 | B8: =IFERROR(INDEX(Productos!$B:$B,MATCH($A8,Productos!$A:$A,0)),"") -> Mango Tommy | C8: 1 | D8: 10 | E8: =C8*D8 -> 10 | F8: 60 | G8: =D8*F8 -> 600 | H8: =E8*F8 -> 600 | I8: Caja de cartón ventilada | J8: Sí | K8: 10 | L8: 13 | M8: 8 | N8: Camión refrigerado | O8: Espinal | P8: CD Bogotá | Q8: 170 | R8: 3.5 | S8: 5
A9: 00226 | B9: =IFERROR(INDEX(Productos!$B:$B,MATCH($A9,Productos!$A:$A,0)),"") -> Cebolla cabezona blanca | C9: 1 | D9: 20 | E9: =C9*D9 -> 20 | F9: 36 | G9: =D9*F9 -> 720 | H9: =E9*F9 -> 720 | I9: Malla en bulto | J9: No | K9: 15 | L9: 25 | M9: 30 | N9: Furgón seco | O9: Tunja | P9: CD Bogotá | Q9: 145 | R9: 3 | S9: 4
A10: 00227 | B10: =IFERROR(INDEX(Productos!$B:$B,MATCH($A10,Productos!$A:$A,0)),"") -> Leche entera pasteurizada | C10: 1.05 | D10: 12 | E10: =C10*D10 -> 12.6 | F10: 56 | G10: =D10*F10 -> 672 | H10: =E10*F10 -> 705.6 | I10: Canasta plástica | J10: Sí | K10: 2 | L10: 6 | M10: 10 | N10: Camión refrigerado | O10: Medellín | P10: CD Bogotá | Q10: 415 | R10: 9.5 | S10: 3
A11: 00228 | B11: =IFERROR(INDEX(Productos!$B:$B,MATCH($A11,Productos!$A:$A,0)),"") -> Yogurt entero | C11: 1.05 | D11: 12 | E11: =C11*D11 -> 12.6 | F11: 60 | G11: =D11*F11 -> 720 | H11: =E11*F11 -> 756 | I11: Canasta plástica | J11: Sí | K11: 2 | L11: 6 | M11: 30 | N11: Camión refrigerado | O11: Sopó | P11: CD Cali | Q11: 480 | R11: 10 | S11: 4
A12: 00229 | B12: =IFERROR(INDEX(Productos!$B:$B,MATCH($A12,Productos!$A:$A,0)),"") -> Queso campesino | C12: 0.5 | D12: 10 | E12: =C12*D12 -> 5 | F12: 120 | G12: =D12*F12 -> 1200 | H12: =E12*F12 -> 600 | I12: Caja de cartón | J12: Sí | K12: 2 | L12: 6 | M12: 30 | N12: Camión refrigerado | O12: Medellín | P12: CD Cali | Q12: 430 | R12: 9 | S12: 5
A13: 00230 | B13: =IFERROR(INDEX(Productos!$B:$B,MATCH($A13,Productos!$A:$A,0)),"") -> Salchichas tipo Viena | C13: 0.45 | D13: 20 | E13: =C13*D13 -> 9 | F13: 80 | G13: =D13*F13 -> 1600 | H13: =E13*F13 -> 720 | I13: Caja de cartón | J13: Sí | K13: 0 | L13: 4 | M13: 60 | N13: Camión refrigerado | O13: Medellín | P13: CD Barranquilla | Q13: 690 | R13: 14 | S13: 5
... A30: 00247 | B30: =IFERROR(INDEX(Productos!$B:$B,MATCH($A30,Productos!$A:$A,0)),"") -> Galletas Saltín | C30: 0.3 | D30: 20 | E30: =C30*D30 -> 6 | F30: 110 | G30: =D30*F30 -> 2200 | H30: =E30*F30 -> 660 | I30: Caja de cartón | J30: No | K30: 15 | L30: 30 | M30: 180 | N30: Furgón seco | O30: Medellín | P30: CD Bogotá | Q30: 415 | R30: 9.5 | S30: 5
A31: 00248 | B31: =IFERROR(INDEX(Productos!$B:$B,MATCH($A31,Productos!$A:$A,0)),"") -> Papel higiénico | C31: 1.2 | D31: 4 | E31: =C31*D31 -> 4.8 | F31: 80 | G31: =D31*F31 -> 320 | H31: =E31*F31 -> 384 | I31: Termoencogible | J31: No | K31: 15 | L31: 30 | M31: N/A | N31: Tractomula con furgón seco | O31: Medellín | P31: CD Bogotá | Q31: 415 | R31: 9.5 | S31: 6

Sheet Tiendas
A1: ID tienda | B1: Tienda | C1: Cadena | D1: Formato | E1: Ciudad | F1: Departamento | G1: CD que abastece | H1: Tiempo desde CD (h) | I1: Frecuencia de reabastecimiento | J1: Cuarto frío en bodega
A2: T01 | B2: Éxito Medellín | C2: Éxito | D2: Hipermercado | E2: Medellín | F2: Antioquia | G2: CD Medellín | H2: 1 | I2: Diaria | J2: Sí
A3: T02 | B3: Jumbo Bogotá | C3: Jumbo | D3: Hipermercado | E3: Bogotá D.C. | F3: Cundinamarca | G3: CD Bogotá | H3: 1.5 | I3: Diaria | J3: Sí
A4: T03 | B4: Carulla Bogotá | C4: Carulla | D4: Supermercado premium | E4: Bogotá D.C. | F4: Cundinamarca | G4: CD Bogotá | H4: 1.5 | I4: Diaria | J4: Sí
A5: T04 | B5: Olímpica Barranquilla | C5: Olímpica | D5: Supermercado | E5: Barranquilla | F5: Atlántico | G5: CD Barranquilla | H5: 1 | I5: Diaria | J5: Sí
A6: T05 | B6: D1 Cali | C6: D1 | D6: Tienda de descuento | E6: Cali | F6: Valle del Cauca | G6: CD Cali | H6: 1.5 | I6: Cada 2 días | J6: Sí
A7: T06 | B7: Ara Medellín | C7: Ara | D7: Tienda de descuento | E7: Medellín | F7: Antioquia | G7: CD Medellín | H7: 1.5 | I7: Cada 2 días | J7: Sí
A8: T07 | B8: Makro Cali | C8: Makro | D8: Mayorista | E8: Cali | F8: Valle del Cauca | G8: CD Cali | H8: 1 | I8: Semanal | J8: Sí
A9: T08 | B9: Justo & Bueno Bogotá | C9: Justo & Bueno | D9: Tienda de descuento | E9: Bogotá D.C. | F9: Cundinamarca | G9: CD Bogotá | H9: 2 | I9: Cada 2 días | J9: No
A10: T09 | B10: Surtimax Bucaramanga | C10: Surtimax | D10: Supermercado | E10: Bucaramanga | F10: Santander | G10: CD Bogotá | H10: 9 | I10: Semanal | J10: Sí
A11: T10 | B11: Éxito Cartagena | C11: Éxito | D11: Supermercado | E11: Cartagena | F11: Bolívar | G11: CD Cartagena | H11: 1.5 | I11: Diaria | J11: Sí
A12: T11 | B12: Tienda de barrio Bogotá | C12: Tienda de barrio | D12: Tienda tradicional | E12: Bogotá D.C. | F12: Cundinamarca | G12: CD Bogotá | H12: 2 | I12: Semanal | J12: No

Sheet Inventario
A1: ID | B1: SKU | C1: Producto | D1: ID tienda | E1: Tienda | F1: Ciudad | G1: Precio (COP) | H1: Stock (und) | I1: Stock mínimo (und) | J1: Estado | K1: Valor inventario (COP)
A2: INV001 | B2: 00241 | C2: =IFERROR(INDEX(Productos!$B:$B,MATCH($B2,Productos!$A:$A,0)),"") -> Huevos AA | D2: T04 | E2: =IFERROR(INDEX(Tiendas!$B:$B,MATCH($D2,Tiendas!$A:$A,0)),"") -> Olímpica Barranquilla | F2: =IFERROR(INDEX(Tiendas!$E:$E,MATCH($D2,Tiendas!$A:$A,0)),"") -> Barranquilla | G2: 23200 | H2: 50 | I2: 40 | J2: =IF(H2<I2,"Reabastecer","OK") -> OK | K2: =G2*H2 -> 1160000
A3: INV002 | B3: 00231 | C3: =IFERROR(INDEX(Productos!$B:$B,MATCH($B3,Productos!$A:$A,0)),"") -> Pulpa de mora congelada | D3: T01 | E3: =IFERROR(INDEX(Tiendas!$B:$B,MATCH($D3,Tiendas!$A:$A,0)),"") -> Éxito Medellín | F3: =IFERROR(INDEX(Tiendas!$E:$E,MATCH($D3,Tiendas!$A:$A,0)),"") -> Medellín | G3: 9300 | H3: 214 | I3: 154 | J3: =IF(H3<I3,"Reabastecer","OK") -> OK | K3: =G3*H3 -> 1990200
A4: INV003 | B4: 00222 | C4: =IFERROR(INDEX(Productos!$B:$B,MATCH($B4,Productos!$A:$A,0)),"") -> Plátano hartón | D4: T09 | E4: =IFERROR(INDEX(Tiendas!$B:$B,MATCH($D4,Tiendas!$A:$A,0)),"") -> Surtimax Bucaramanga | F4: =IFERROR(INDEX(Tiendas!$E:$E,MATCH($D4,Tiendas!$A:$A,0)),"") -> Bucaramanga | G4: 4100 | H4: 116 | I4: 86 | J4: =IF(H4<I4,"Reabastecer","OK") -> OK | K4: =G4*H4 -> 475600
A5: INV004 | B5: 00232 | C5: =IFERROR(INDEX(Productos!$B:$B,MATCH($B5,Productos!$A:$A,0)),"") -> Arroz blanco | D5: T10 | E5: =IFERROR(INDEX(Tiendas!$B:$B,MATCH($D5,Tiendas!$A:$A,0)),"") -> Éxito Cartagena | F5: =IFERROR(INDEX(Tiendas!$E:$E,MATCH($D5,Tiendas!$A:$A,0)),"") -> Cartagena | G5: 5800 | H5: 42 | I5: 19 | J5: =IF(H5<I5,"Reabastecer","OK") -> OK | K5: =G5*H5 -> 243600
A6: INV005 | B6: 00248 | C6: =IFERROR(INDEX(Productos!$B:$B,MATCH($B6,Productos!$A:$A,0)),"") -> Papel higiénico | D6: T01 | E6: =IFERROR(INDEX(Tiendas!$B:$B,MATCH($D6,Tiendas!$A:$A,0)),"") -> Éxito Medellín | F6: =IFERROR(INDEX(Tiendas!$E:$E,MATCH($D6,Tiendas!$A:$A,0)),"") -> Medellín | G6: 23900 | H6: 174 | I6: 126 | J6: =IF(H6<I6,"Reabastecer","OK") -> OK | K6: =G6*H6 -> 4158600
A7: INV006 | B7: 00219 | C7: =IFERROR(INDEX(Productos!$B:$B,MATCH($B7,Productos!$A:$A,0)),"") -> Banano premium | D7: T06 | E7: =IFERROR(INDEX(Tiendas!$B:$B,MATCH($D7,Tiendas!$A:$A,0)),"") -> Ara Medellín | F7: =IFERROR(INDEX(Tiendas!$E:$E,MATCH($D7,Tiendas!$A:$A,0)),"") -> Medellín | G7: 4000 | H7: 41 | I7: 29 | J7: =IF(H7<I7,"Reabastecer","OK") -> OK | K7: =G7*H7 -> 164000
A8: INV007 | B8: 00231 | C8: =IFERROR(INDEX(Productos!$B:$B,MATCH($B8,Productos!$A:$A,0)),"") -> Pulpa de mora congelada | D8: T05 | E8: =IFERROR(INDEX(Tiendas!$B:$B,MATCH($D8,Tiendas!$A:$A,0)),"") -> D1 Cali | F8: =IFERROR(INDEX(Tiendas!$E:$E,MATCH($D8,Tiendas!$A:$A,0)),"") -> Cali | G8: 10200 | H8: 131 | I8: 83 | J8: =IF(H8<I8,"Reabastecer","OK") -> OK | K8: =G8*H8 -> 1336200
A9: INV008 | B9: 00240 | C9: =IFERROR(INDEX(Productos!$B:$B,MATCH($B9,Productos!$A:$A,0)),"") -> Arequipe | D9: T02 | E9: =IFERROR(INDEX(Tiendas!$B:$B,MATCH($D9,Tiendas!$A:$A,0)),"") -> Jumbo Bogotá | F9: =IFERROR(INDEX(Tiendas!$E:$E,MATCH($D9,Tiendas!$A:$A,0)),"") -> Bogotá D.C. | G9: 8600 | H9: 65 | I9: 87 | J9: =IF(H9<I9,"Reabastecer","OK") -> Reabastecer | K9: =G9*H9 -> 559000
A10: INV009 | B10: 00243 | C10: =IFERROR(INDEX(Productos!$B:$B,MATCH($B10,Productos!$A:$A,0)),"") -> Aguardiente tradicional | D10: T02 | E10: =IFERROR(INDEX(Tiendas!$B:$B,MATCH($D10,Tiendas!$A:$A,0)),"") -> Jumbo Bogotá | F10: =IFERROR(INDEX(Tiendas!$E:$E,MATCH($D10,Tiendas!$A:$A,0)),"") -> Bogotá D.C. | G10: 58700 | H10: 265 | I10: 164 | J10: =IF(H10<I10,"Reabastecer","OK") -> OK | K10: =G10*H10 -> 15555500
A11: INV010 | B11: 00246 | C11: =IFERROR(INDEX(Productos!$B:$B,MATCH($B11,Productos!$A:$A,0)),"") -> Papas fritas sabor pollo | D11: T04 | E11: =IFERROR(INDEX(Tiendas!$B:$B,MATCH($D11,Tiendas!$A:$A,0)),"") -> Olímpica Barranquilla | F11: =IFERROR(INDEX(Tiendas!$E:$E,MATCH($D11,Tiendas!$A:$A,0)),"") -> Barranquilla | G11: 5000 | H11: 17 | I11: 13 | J11: =IF(H11<I11,"Reabastecer","OK") -> OK | K11: =G11*H11 -> 85000
A12: INV011 | B12: 00236 | C12: =IFERROR(INDEX(Productos!$B:$B,MATCH($B12,Productos!$A:$A,0)),"") -> Chocolate de mesa | D12: T02 | E12: =IFERROR(INDEX(Tiendas!$B:$B,MATCH($D12,Tiendas!$A:$A,0)),"") -> Jumbo Bogotá | F12: =IFERROR(INDEX(Tiendas!$E:$E,MATCH($D12,Tiendas!$A:$A,0)),"") -> Bogotá D.C. | G12: 17200 | H12: 36 | I12: 47 | J12: =IF(H12<I12,"Reabastecer","OK") -> Reabastecer | K12: =G12*H12 -> 619200
A13: INV012 | B13: 00233 | C13: =IFERROR(INDEX(Productos!$B:$B,MATCH($B13,Productos!$A:$A,0)),"") -> Panela cuadrada | D13: T06 | E13: =IFERROR(INDEX(Tiendas!$B:$B,MATCH($D13,Tiendas!$A:$A,0)),"") -> Ara Medellín | F13: =IFERROR(INDEX(Tiendas!$E:$E,MATCH($D13,Tiendas!$A:$A,0)),"") -> Medellín | G13: 5400 | H13: 95 | I13: 52 | J13: =IF(H13<I13,"Reabastecer","OK") -> OK | K13: =G13*H13 -> 513000
... A91: INV090 | B91: 00241 | C91: =IFERROR(INDEX(Productos!$B:$B,MATCH($B91,Productos!$A:$A,0)),"") -> Huevos AA | D91: T01 | E91: =IFERROR(INDEX(Tiendas!$B:$B,MATCH($D91,Tiendas!$A:$A,0)),"") -> Éxito Medellín | F91: =IFERROR(INDEX(Tiendas!$E:$E,MATCH($D91,Tiendas!$A:$A,0)),"") -> Medellín | G91: 21500 | H91: 359 | I91: 184 | J91: =IF(H91<I91,"Reabastecer","OK") -> OK | K91: =G91*H91 -> 7718500

Sheet Trivia
A1: ID | B1: Tema | C1: Afirmación | D1: Respuesta correcta | E1: Explicación (se muestra al responder) | F1: Dificultad | G1: SKU relacionado | H1: Producto relacionado | I1: Fuente del dato | J1: Puntos | K1: Activa
A2: TRV001 | B2: Origen y producto | C2: La conservación recomendada de «Plátano hartón» es: congelado -18 °C. | D2: Falso | E2: Falso: la conservación recomendada de «Plátano hartón» es temperatura ambiente. | F2: Fácil | G2: 00222 | H2: =IF(G2="","",IFERROR(INDEX(Productos!$B:$B,MATCH(G2,Productos!$A:$A,0)),"")) -> Plátano hartón | I2: Productos · Conservación | J2: =IF(F2="Fácil",10,IF(F2="Media",20,30)) -> 10 | K2: Sí
A3: TRV002 | B3: Transporte y rutas | C3: «Arequipe» se despacha desde Sopó hacia el CD Cali. | D3: Falso | E3: Falso: «Arequipe» sale de Sopó hacia el CD Medellín (~430 km). | F3: Media | G3: 00240 | H3: =IF(G3="","",IFERROR(INDEX(Productos!$B:$B,MATCH(G3,Productos!$A:$A,0)),"")) -> Arequipe | I3: Logística · Origen de despacho y CD destino | J3: =IF(F3="Fácil",10,IF(F3="Media",20,30)) -> 20 | K3: Sí
A4: TRV003 | B4: Cadena de frío | C4: Para transportar «Queso campesino» (Colanta) se debe mantener una temperatura entre 2 °C y 6 °C. | D4: Verdadero | E4: Verdadero: el rango de transporte de «Queso campesino» es de 2 °C a 6 °C. | F4: Fácil | G4: 00229 | H4: =IF(G4="","",IFERROR(INDEX(Productos!$B:$B,MATCH(G4,Productos!$A:$A,0)),"")) -> Queso campesino | I4: Logística · Temp. transporte mín/máx | J4: =IF(F4="Fácil",10,IF(F4="Media",20,30)) -> 10 | K4: Sí
A5: TRV004 | B5: Cadena de frío | C5: «Papel higiénico» (Familia) debe transportarse congelado a -18 °C. | D5: Falso | E5: Falso: «Papel higiénico» se transporta en condiciones secas/ambiente (15–30 °C), sin cadena de frío. | F5: Fácil | G5: 00248 | H5: =IF(G5="","",IFERROR(INDEX(Productos!$B:$B,MATCH(G5,Productos!$A:$A,0)),"")) -> Papel higiénico | I5: Logística · Transporte con temp. controlada | J5: =IF(F5="Fácil",10,IF(F5="Media",20,30)) -> 10 | K5: Sí
A6: TRV005 | B6: Origen y producto | C6: «Gaseosa Colombiana» (Postobón) tiene origen en Antioquia. | D6: Verdadero | E6: Verdadero: el origen de referencia de «Gaseosa Colombiana» es Antioquia. | F6: Fácil | G6: 00242 | H6: =IF(G6="","",IFERROR(INDEX(Productos!$B:$B,MATCH(G6,Productos!$A:$A,0)),"")) -> Gaseosa Colombiana | I6: Productos · Origen | J6: =IF(F6="Fácil",10,IF(F6="Media",20,30)) -> 10 | K6: Sí
A7: TRV006 | B7: Conceptos de logística | C7: El lead time es el tiempo que transcurre entre hacer un pedido y recibirlo. | D7: Verdadero | E7: Incluye preparación, transporte y recepción. | F7: Media | H7: =IF(G7="","",IFERROR(INDEX(Productos!$B:$B,MATCH(G7,Productos!$A:$A,0)),"")) | I7: Conocimiento general | J7: =IF(F7="Fácil",10,IF(F7="Media",20,30)) -> 20 | K7: Sí
A8: TRV007 | B8: Paletizado y embalaje | C8: Una estiba de «Panela cuadrada» se arma con 60 cajas. | D8: Falso | E8: Falso: una estiba de «Panela cuadrada» lleva 40 cajas. | F8: Difícil | G8: 00233 | H8: =IF(G8="","",IFERROR(INDEX(Productos!$B:$B,MATCH(G8,Productos!$A:$A,0)),"")) -> Panela cuadrada | I8: Logística · Cajas por estiba | J8: =IF(F8="Fácil",10,IF(F8="Media",20,30)) -> 30 | K8: Sí
A9: TRV008 | B9: Paletizado y embalaje | C9: Cada caja de «Banano premium» contiene 36 unidades. | D9: Falso | E9: Falso: cada caja de «Banano premium» trae 18 unidades. | F9: Difícil | G9: 00219 | H9: =IF(G9="","",IFERROR(INDEX(Productos!$B:$B,MATCH(G9,Productos!$A:$A,0)),"")) -> Banano premium | I9: Logística · Unidades por caja | J9: =IF(F9="Fácil",10,IF(F9="Media",20,30)) -> 30 | K9: Sí
A10: TRV009 | B10: Conceptos de logística | C10: FIFO significa «primero en entrar, primero en salir». | D10: Verdadero | E10: FIFO despacha primero lo que llegó primero a la bodega. | F10: Fácil | H10: =IF(G10="","",IFERROR(INDEX(Productos!$B:$B,MATCH(G10,Productos!$A:$A,0)),"")) | I10: Conocimiento general | J10: =IF(F10="Fácil",10,IF(F10="Media",20,30)) -> 10 | K10: Sí
A11: TRV010 | B11: Inventario en tienda | C11: D1 Cali se abastece desde el CD Cali. | D11: Verdadero | E11: Verdadero: D1 Cali recibe mercancía del CD Cali. | F11: Media | H11: =IF(G11="","",IFERROR(INDEX(Productos!$B:$B,MATCH(G11,Productos!$A:$A,0)),"")) | I11: Tiendas · CD que abastece | J11: =IF(F11="Fácil",10,IF(F11="Media",20,30)) -> 20 | K11: Sí
A12: TRV011 | B12: Conceptos de logística | C12: La trazabilidad por lote permite saber de dónde viene un producto y a qué tiendas fue enviado. | D12: Verdadero | E12: Es fundamental para retiros del mercado y control de calidad. | F12: Media | H12: =IF(G12="","",IFERROR(INDEX(Productos!$B:$B,MATCH(G12,Productos!$A:$A,0)),"")) | I12: Conocimiento general | J12: =IF(F12="Fácil",10,IF(F12="Media",20,30)) -> 20 | K12: Sí
A13: TRV012 | B13: Conceptos de logística | C13: Un centro de distribución (CD) es un lugar donde el cliente final compra directamente. | D13: Falso | E13: El CD recibe, almacena y despacha a las tiendas; no vende al público. | F13: Fácil | H13: =IF(G13="","",IFERROR(INDEX(Productos!$B:$B,MATCH(G13,Productos!$A:$A,0)),"")) | I13: Conocimiento general | J13: =IF(F13="Fácil",10,IF(F13="Media",20,30)) -> 10 | K13: Sí
A14: TRV013 | B14: Conceptos de logística | C14: El prefijo 770 en un código de barras GS1 corresponde a productos registrados en Colombia. | D14: Verdadero | E14: 770 es el prefijo GS1 asignado a Colombia. | F14: Difícil | H14: =IF(G14="","",IFERROR(INDEX(Productos!$B:$B,MATCH(G14,Productos!$A:$A,0)),"")) | I14: Conocimiento general | J14: =IF(F14="Fácil",10,IF(F14="Media",20,30)) -> 30 | K14: Sí
A15: TRV014 | B15: Conceptos de logística | C15: Un producto congelado puede pasar varias horas a 25 °C y volver a congelarse sin afectar su calidad ni su inocuidad. | D15: Falso | E15: Romper la cadena de frío afecta la calidad y aumenta el riesgo microbiológico. | F15: Media | H15: =IF(G15="","",IFERROR(INDEX(Productos!$B:$B,MATCH(G15,Productos!$A:$A,0)),"")) | I15: Conocimiento general | J15: =IF(F15="Fácil",10,IF(F15="Media",20,30)) -> 20 | K15: Sí
A16: TRV015 | B16: Origen y producto | C16: «Chocolate de mesa» (Corona) tiene origen en Antioquia. | D16: Verdadero | E16: Verdadero: el origen de referencia de «Chocolate de mesa» es Antioquia. | F16: Fácil | G16: 00236 | H16: =IF(G16="","",IFERROR(INDEX(Productos!$B:$B,MATCH(G16,Productos!$A:$A,0)),"")) -> Chocolate de mesa | I16: Productos · Origen | J16: =IF(F16="Fácil",10,IF(F16="Media",20,30)) -> 10 | K16: Sí
A17: TRV016 | B17: Cadena de frío | C17: Para transportar «Leche entera pasteurizada» (Colanta) se debe mantener una temperatura entre 2 °C y 6 °C. | D17: Verdadero | E17: Verdadero: el rango de transporte de «Leche entera pasteurizada» es de 2 °C a 6 °C. | F17: Fácil | G17: 00227 | H17: =IF(G17="","",IFERROR(INDEX(Productos!$B:$B,MATCH(G17,Productos!$A:$A,0)),"")) -> Leche entera pasteurizada | I17: Logística · Temp. transporte mín/máx | J17: =IF(F17="Fácil",10,IF(F17="Media",20,30)) -> 10 | K17: Sí
A18: TRV017 | B18: Conceptos de logística | C18: El prefijo 770 en un código de barras GS1 corresponde a productos registrados en México. | D18: Falso | E18: 770 es el de Colombia; México usa 750. | F18: Difícil | H18: =IF(G18="","",IFERROR(INDEX(Productos!$B:$B,MATCH(G18,Productos!$A:$A,0)),"")) | I18: Conocimiento general | J18: =IF(F18="Fácil",10,IF(F18="Media",20,30)) -> 30 | K18: Sí
A19: TRV018 | B19: Conceptos de logística | C19: Una estiba (pallet) permite agrupar cajas para moverlas con montacargas o apilador. | D19: Verdadero | E19: Facilita el manejo, transporte y almacenamiento de carga unitizada. | F19: Fácil | H19: =IF(G19="","",IFERROR(INDEX(Productos!$B:$B,MATCH(G19,Productos!$A:$A,0)),"")) | I19: Conocimiento general | J19: =IF(F19="Fácil",10,IF(F19="Media",20,30)) -> 10 | K19: Sí
A20: TRV019 | B20: Paletizado y embalaje | C20: Una estiba de «Huevos AA» se arma con 45 cajas. | D20: Falso | E20: Falso: una estiba de «Huevos AA» lleva 30 cajas. | F20: Difícil | G20: 00241 | H20: =IF(G20="","",IFERROR(INDEX(Productos!$B:$B,MATCH(G20,Productos!$A:$A,0)),"")) -> Huevos AA | I20: Logística · Cajas por estiba | J20: =IF(F20="Fácil",10,IF(F20="Media",20,30)) -> 30 | K20: Sí
A21: TRV020 | B21: Conceptos de logística | C21: FEFO significa «primero en vencer, primero en salir». | D21: Verdadero | E21: FEFO (First Expired, First Out) prioriza despachar lo que vence antes; es clave en perecederos. | F21: Fácil | H21: =IF(G21="","",IFERROR(INDEX(Productos!$B:$B,MATCH(G21,Productos!$A:$A,0)),"")) | I21: Conocimiento general | J21: =IF(F21="Fácil",10,IF(F21="Media",20,30)) -> 10 | K21: Sí
A22: TRV021 | B22: Paletizado y embalaje | C22: Una estiba de «Aguacate Hass» se arma con 64 cajas. | D22: Verdadero | E22: Verdadero: una estiba de «Aguacate Hass» lleva 64 cajas. | F22: Difícil | G22: 00220 | H22: =IF(G22="","",IFERROR(INDEX(Productos!$B:$B,MATCH(G22,Productos!$A:$A,0)),"")) -> Aguacate Hass | I22: Logística · Cajas por estiba | J22: =IF(F22="Fácil",10,IF(F22="Media",20,30)) -> 30 | K22: Sí
A23: TRV022 | B23: Cadena de frío | C23: «Gaseosa Colombiana» (Postobón) debe transportarse congelado a -18 °C. | D23: Falso | E23: Falso: «Gaseosa Colombiana» se transporta en condiciones secas/ambiente (10–30 °C), sin cadena de frío. | F23: Fácil | G23: 00242 | H23: =IF(G23="","",IFERROR(INDEX(Productos!$B:$B,MATCH(G23,Productos!$A:$A,0)),"")) -> Gaseosa Colombiana | I23: Logística · Transporte con temp. controlada | J23: =IF(F23="Fácil",10,IF(F23="Media",20,30)) -> 10 | K23: Sí
A24: TRV023 | B24: Vida útil y rotación | C24: La vida útil estimada de «Uchuva con capacho» es de 15 días. | D24: Verdadero | E24: Verdadero: la vida útil estimada de «Uchuva con capacho» es de 15 días. | F24: Media | G24: 00223 | H24: =IF(G24="","",IFERROR(INDEX(Productos!$B:$B,MATCH(G24,Productos!$A:$A,0)),"")) -> Uchuva con capacho | I24: Logística · Vida útil (días) | J24: =IF(F24="Fácil",10,IF(F24="Media",20,30)) -> 20 | K24: Sí
A25: TRV024 | B25: Origen y producto | C25: «Leche entera pasteurizada» (Colanta) tiene origen en Cundinamarca. | D25: Falso | E25: Falso: el origen de referencia de «Leche entera pasteurizada» es Antioquia. | F25: Fácil | G25: 00227 | H25: =IF(G25="","",IFERROR(INDEX(Productos!$B:$B,MATCH(G25,Productos!$A:$A,0)),"")) -> Leche entera pasteurizada | I25: Productos · Origen | J25: =IF(F25="Fácil",10,IF(F25="Media",20,30)) -> 10 | K25: Sí
A26: TRV025 | B26: Inventario en tienda | C26: En Éxito Medellín, «Yogurt entero» tiene un stock por debajo del mínimo y requiere reabastecimiento. | D26: Verdadero | E26: Verdadero: el stock (19) es menor al mínimo (41). | F26: Media | G26: 00228 | H26: =IF(G26="","",IFERROR(INDEX(Productos!$B:$B,MATCH(G26,Productos!$A:$A,0)),"")) -> Yogurt entero | I26: Inventario · Estado | J26: =IF(F26="Fácil",10,IF(F26="Media",20,30)) -> 20 | K26: Sí
A27: TRV026 | B27: Inventario en tienda | C27: Éxito Medellín cuenta con cuarto frío en su bodega. | D27: Verdadero | E27: Verdadero: Éxito Medellín tiene cuarto frío. | F27: Fácil | H27: =IF(G27="","",IFERROR(INDEX(Productos!$B:$B,MATCH(G27,Productos!$A:$A,0)),"")) | I27: Tiendas · Cuarto frío | J27: =IF(F27="Fácil",10,IF(F27="Media",20,30)) -> 10 | K27: Sí
A28: TRV027 | B28: Origen y producto | C28: «Cebolla cabezona blanca» (Frescura) tiene origen en Boyacá. | D28: Verdadero | E28: Verdadero: el origen de referencia de «Cebolla cabezona blanca» es Boyacá. | F28: Fácil | G28: 00226 | H28: =IF(G28="","",IFERROR(INDEX(Productos!$B:$B,MATCH(G28,Productos!$A:$A,0)),"")) -> Cebolla cabezona blanca | I28: Productos · Origen | J28: =IF(F28="Fácil",10,IF(F28="Media",20,30)) -> 10 | K28: Sí
A29: TRV028 | B29: Transporte y rutas | C29: El vehículo típico para mover «Chocolatina Jet» es: furgón seco. | D29: Verdadero | E29: Verdadero: el vehículo típico para «Chocolatina Jet» es furgón seco. | F29: Media | G29: 00245 | H29: =IF(G29="","",IFERROR(INDEX(Productos!$B:$B,MATCH(G29,Productos!$A:$A,0)),"")) -> Chocolatina Jet | I29: Logística · Vehículo | J29: =IF(F29="Fácil",10,IF(F29="Media",20,30)) -> 20 | K29: Sí
A30: TRV029 | B30: Paletizado y embalaje | C30: Cada caja de «Pulpa de mora congelada» contiene 40 unidades. | D30: Falso | E30: Falso: cada caja de «Pulpa de mora congelada» trae 20 unidades. | F30: Difícil | G30: 00231 | H30: =IF(G30="","",IFERROR(INDEX(Productos!$B:$B,MATCH(G30,Productos!$A:$A,0)),"")) -> Pulpa de mora congelada | I30: Logística · Unidades por caja | J30: =IF(F30="Fácil",10,IF(F30="Media",20,30)) -> 30 | K30: Sí
A31: TRV030 | B31: Cadena de frío | C31: «Bocadillo veleño» (Frescura) no necesita transporte con temperatura controlada. | D31: Verdadero | E31: Verdadero: «Bocadillo veleño» se transporta en condiciones secas/ambiente (15–30 °C), sin cadena de frío. | F31: Fácil | G31: 00239 | H31: =IF(G31="","",IFERROR(INDEX(Productos!$B:$B,MATCH(G31,Productos!$A:$A,0)),"")) -> Bocadillo veleño | I31: Logística · Transporte con temp. controlada | J31: =IF(F31="Fácil",10,IF(F31="Media",20,30)) -> 10 | K31: Sí
A32: TRV031 | B32: Conceptos de logística | C32: Dos presentaciones distintas de un mismo producto (500 g y 1 kg) deben compartir el mismo SKU. | D32: Falso | E32: Cada presentación se registra con un SKU distinto. | F32: Fácil | H32: =IF(G32="","",IFERROR(INDEX(Productos!$B:$B,MATCH(G32,Productos!$A:$A,0)),"")) | I32: Conocimiento general | J32: =IF(F32="Fácil",10,IF(F32="Media",20,30)) -> 10 | K32: Sí
A33: TRV032 | B33: Inventario en tienda | C33: Éxito Medellín se abastece desde el CD Medellín. | D33: Verdadero | E33: Verdadero: Éxito Medellín recibe mercancía del CD Medellín. | F33: Media | H33: =IF(G33="","",IFERROR(INDEX(Productos!$B:$B,MATCH(G33,Productos!$A:$A,0)),"")) | I33: Tiendas · CD que abastece | J33: =IF(F33="Fácil",10,IF(F33="Media",20,30)) -> 20 | K33: Sí
A34: TRV033 | B34: Origen y producto | C34: «Aceite de girasol» (Gourmet) tiene origen en Boyacá. | D34: Falso | E34: Falso: el origen de referencia de «Aceite de girasol» es Valle del Cauca. | F34: Fácil | G34: 00237 | H34: =IF(G34="","",IFERROR(INDEX(Productos!$B:$B,MATCH(G34,Productos!$A:$A,0)),"")) -> Aceite de girasol | I34: Productos · Origen | J34: =IF(F34="Fácil",10,IF(F34="Media",20,30)) -> 10 | K34: Sí
A35: TRV034 | B35: Origen y producto | C35: «Aguardiente tradicional» (Antioqueño) tiene origen en Cundinamarca. | D35: Falso | E35: Falso: el origen de referencia de «Aguardiente tradicional» es Antioquia. | F35: Fácil | G35: 00243 | H35: =IF(G35="","",IFERROR(INDEX(Productos!$B:$B,MATCH(G35,Productos!$A:$A,0)),"")) -> Aguardiente tradicional | I35: Productos · Origen | J35: =IF(F35="Fácil",10,IF(F35="Media",20,30)) -> 10 | K35: Sí
A36: TRV035 | B36: Transporte y rutas | C36: El vehículo típico para mover «Mango Tommy» es: camión refrigerado. | D36: Verdadero | E36: Verdadero: el vehículo típico para «Mango Tommy» es camión refrigerado. | F36: Media | G36: 00225 | H36: =IF(G36="","",IFERROR(INDEX(Productos!$B:$B,MATCH(G36,Productos!$A:$A,0)),"")) -> Mango Tommy | I36: Logística · Vehículo | J36: =IF(F36="Fácil",10,IF(F36="Media",20,30)) -> 20 | K36: Sí
A37: TRV036 | B37: Origen y producto | C37: «Papa criolla lavada» (Frescura) tiene origen en Huila. | D37: Falso | E37: Falso: el origen de referencia de «Papa criolla lavada» es Cundinamarca. | F37: Fácil | G37: 00221 | H37: =IF(G37="","",IFERROR(INDEX(Productos!$B:$B,MATCH(G37,Productos!$A:$A,0)),"")) -> Papa criolla lavada | I37: Productos · Origen | J37: =IF(F37="Fácil",10,IF(F37="Media",20,30)) -> 10 | K37: Sí
A38: TRV037 | B38: Origen y producto | C38: «Arroz blanco» (Diana) tiene origen en Tolima. | D38: Verdadero | E38: Verdadero: el origen de referencia de «Arroz blanco» es Tolima. | F38: Fácil | G38: 00232 | H38: =IF(G38="","",IFERROR(INDEX(Productos!$B:$B,MATCH(G38,Productos!$A:$A,0)),"")) -> Arroz blanco | I38: Productos · Origen | J38: =IF(F38="Fácil",10,IF(F38="Media",20,30)) -> 10 | K38: Sí
A39: TRV038 | B39: Inventario en tienda | C39: Ara Medellín se abastece desde el CD Cali. | D39: Falso | E39: Falso: Ara Medellín recibe mercancía del CD Medellín. | F39: Media | H39: =IF(G39="","",IFERROR(INDEX(Productos!$B:$B,MATCH(G39,Productos!$A:$A,0)),"")) | I39: Tiendas · CD que abastece | J39: =IF(F39="Fácil",10,IF(F39="Media",20,30)) -> 20 | K39: Sí
A40: TRV039 | B40: Origen y producto | C40: «Café tostado y molido» (Juan Valdez) tiene origen en Huila. | D40: Verdadero | E40: Verdadero: el origen de referencia de «Café tostado y molido» es Huila. | F40: Fácil | G40: 00234 | H40: =IF(G40="","",IFERROR(INDEX(Productos!$B:$B,MATCH(G40,Productos!$A:$A,0)),"")) -> Café tostado y molido | I40: Productos · Origen | J40: =IF(F40="Fácil",10,IF(F40="Media",20,30)) -> 10 | K40: Sí
A41: TRV040 | B41: Cadena de frío | C41: «Cebolla cabezona blanca» (Frescura) debe transportarse congelado a -18 °C. | D41: Falso | E41: Falso: «Cebolla cabezona blanca» se transporta en condiciones secas/ambiente (15–25 °C), sin cadena de frío. | F41: Fácil | G41: 00226 | H41: =IF(G41="","",IFERROR(INDEX(Productos!$B:$B,MATCH(G41,Productos!$A:$A,0)),"")) -> Cebolla cabezona blanca | I41: Logística · Transporte con temp. controlada | J41: =IF(F41="Fácil",10,IF(F41="Media",20,30)) -> 10 | K41: Sí
A42: TRV041 | B42: Paletizado y embalaje | C42: Cada caja de «Café tostado y molido» contiene 12 unidades. | D42: Verdadero | E42: Verdadero: cada caja de «Café tostado y molido» trae 12 unidades. | F42: Difícil | G42: 00234 | H42: =IF(G42="","",IFERROR(INDEX(Productos!$B:$B,MATCH(G42,Productos!$A:$A,0)),"")) -> Café tostado y molido | I42: Logística · Unidades por caja | J42: =IF(F42="Fácil",10,IF(F42="Media",20,30)) -> 30 | K42: Sí
A43: TRV042 | B43: Conceptos de logística | C43: El SKU es un código interno que identifica de forma única cada producto o presentación en el inventario. | D43: Verdadero | E43: Cada variante (sabor, tamaño, empaque) tiene su propio SKU. | F43: Fácil | H43: =IF(G43="","",IFERROR(INDEX(Productos!$B:$B,MATCH(G43,Productos!$A:$A,0)),"")) | I43: Conocimiento general | J43: =IF(F43="Fácil",10,IF(F43="Media",20,30)) -> 10 | K43: Sí
A44: TRV043 | B44: Origen y producto | C44: «Queso campesino» (Colanta) tiene origen en Huila. | D44: Falso | E44: Falso: el origen de referencia de «Queso campesino» es Antioquia. | F44: Fácil | G44: 00229 | H44: =IF(G44="","",IFERROR(INDEX(Productos!$B:$B,MATCH(G44,Productos!$A:$A,0)),"")) -> Queso campesino | I44: Productos · Origen | J44: =IF(F44="Fácil",10,IF(F44="Media",20,30)) -> 10 | K44: Sí
A45: TRV044 | B45: Origen y producto | C45: «Salchichas tipo Viena» (Zenú) tiene origen en Antioquia. | D45: Verdadero | E45: Verdadero: el origen de referencia de «Salchichas tipo Viena» es Antioquia. | F45: Fácil | G45: 00230 | H45: =IF(G45="","",IFERROR(INDEX(Productos!$B:$B,MATCH(G45,Productos!$A:$A,0)),"")) -> Salchichas tipo Viena | I45: Productos · Origen | J45: =IF(F45="Fácil",10,IF(F45="Media",20,30)) -> 10 | K45: Sí
A46: TRV045 | B46: Conceptos de logística | C46: Un producto refrigerado y uno congelado se transportan a la misma temperatura. | D46: Falso | E46: Refrigerados: aprox. 0–8 °C. Congelados: aprox. -18 °C o menos. | F46: Fácil | H46: =IF(G46="","",IFERROR(INDEX(Productos!$B:$B,MATCH(G46,Productos!$A:$A,0)),"")) | I46: Conocimiento general | J46: =IF(F46="Fácil",10,IF(F46="Media",20,30)) -> 10 | K46: Sí
A47: TRV046 | B47: Inventario en tienda | C47: Tienda de barrio Bogotá se abastece desde el CD Bogotá. | D47: Verdadero | E47: Verdadero: Tienda de barrio Bogotá recibe mercancía del CD Bogotá. | F47: Media | H47: =IF(G47="","",IFERROR(INDEX(Productos!$B:$B,MATCH(G47,Productos!$A:$A,0)),"")) | I47: Tiendas · CD que abastece | J47: =IF(F47="Fácil",10,IF(F47="Media",20,30)) -> 20 | K47: Sí
A48: TRV047 | B48: Origen y producto | C48: La conservación recomendada de «Gaseosa Colombiana» es: congelado -18 °C. | D48: Falso | E48: Falso: la conservación recomendada de «Gaseosa Colombiana» es temperatura ambiente. | F48: Fácil | G48: 00242 | H48: =IF(G48="","",IFERROR(INDEX(Productos!$B:$B,MATCH(G48,Productos!$A:$A,0)),"")) -> Gaseosa Colombiana | I48: Productos · Conservación | J48: =IF(F48="Fácil",10,IF(F48="Media",20,30)) -> 10 | K48: Sí
A49: TRV048 | B49: Paletizado y embalaje | C49: Cada caja de «Plátano hartón» contiene 15 unidades. | D49: Verdadero | E49: Verdadero: cada caja de «Plátano hartón» trae 15 unidades. | F49: Difícil | G49: 00222 | H49: =IF(G49="","",IFERROR(INDEX(Productos!$B:$B,MATCH(G49,Productos!$A:$A,0)),"")) -> Plátano hartón | I49: Logística · Unidades por caja | J49: =IF(F49="Fácil",10,IF(F49="Media",20,30)) -> 30 | K49: Sí
A50: TRV049 | B50: Vida útil y rotación | C50: La vida útil estimada de «Café instantáneo clásico» es de 720 días. | D50: Verdadero | E50: Verdadero: la vida útil estimada de «Café instantáneo clásico» es de 720 días. | F50: Media | G50: 00235 | H50: =IF(G50="","",IFERROR(INDEX(Productos!$B:$B,MATCH(G50,Productos!$A:$A,0)),"")) -> Café instantáneo clásico | I50: Logística · Vida útil (días) | J50: =IF(F50="Fácil",10,IF(F50="Media",20,30)) -> 20 | K50: Sí
A51: TRV050 | B51: Origen y producto | C51: «Galletas Saltín» (Noel) tiene origen en Santander. | D51: Falso | E51: Falso: el origen de referencia de «Galletas Saltín» es Antioquia. | F51: Fácil | G51: 00247 | H51: =IF(G51="","",IFERROR(INDEX(Productos!$B:$B,MATCH(G51,Productos!$A:$A,0)),"")) -> Galletas Saltín | I51: Productos · Origen | J51: =IF(F51="Fácil",10,IF(F51="Media",20,30)) -> 10 | K51: Sí
A52: TRV051 | B52: Paletizado y embalaje | C52: Cada caja de «Yogurt entero» contiene 12 unidades. | D52: Verdadero | E52: Verdadero: cada caja de «Yogurt entero» trae 12 unidades. | F52: Difícil | G52: 00228 | H52: =IF(G52="","",IFERROR(INDEX(Productos!$B:$B,MATCH(G52,Productos!$A:$A,0)),"")) -> Yogurt entero | I52: Logística · Unidades por caja | J52: =IF(F52="Fácil",10,IF(F52="Media",20,30)) -> 30 | K52: Sí
A53: TRV052 | B53: Inventario en tienda | C53: En Éxito Cartagena, «Arroz blanco» tiene un stock por debajo del mínimo y requiere reabastecimiento. | D53: Falso | E53: Falso: el stock (42) está por encima del mínimo (19), estado OK. | F53: Media | G53: 00232 | H53: =IF(G53="","",IFERROR(INDEX(Productos!$B:$B,MATCH(G53,Productos!$A:$A,0)),"")) -> Arroz blanco | I53: Inventario · Estado | J53: =IF(F53="Fácil",10,IF(F53="Media",20,30)) -> 20 | K53: Sí
A54: TRV053 | B54: Cadena de frío | C54: «Papas fritas sabor pollo» (Margarita) debe transportarse congelado a -18 °C. | D54: Falso | E54: Falso: «Papas fritas sabor pollo» se transporta en condiciones secas/ambiente (15–30 °C), sin cadena de frío. | F54: Fácil | G54: 00246 | H54: =IF(G54="","",IFERROR(INDEX(Productos!$B:$B,MATCH(G54,Productos!$A:$A,0)),"")) -> Papas fritas sabor pollo | I54: Logística · Transporte con temp. controlada | J54: =IF(F54="Fácil",10,IF(F54="Media",20,30)) -> 10 | K54: Sí
A55: TRV054 | B55: Vida útil y rotación | C55: La vida útil estimada de «Galletas Saltín» es de 180 días. | D55: Verdadero | E55: Verdadero: la vida útil estimada de «Galletas Saltín» es de 180 días. | F55: Media | G55: 00247 | H55: =IF(G55="","",IFERROR(INDEX(Productos!$B:$B,MATCH(G55,Productos!$A:$A,0)),"")) -> Galletas Saltín | I55: Logística · Vida útil (días) | J55: =IF(F55="Fácil",10,IF(F55="Media",20,30)) -> 20 | K55: Sí
A56: TRV055 | B56: Transporte y rutas | C56: El vehículo típico para mover «Queso campesino» es: camión refrigerado. | D56: Verdadero | E56: Verdadero: el vehículo típico para «Queso campesino» es camión refrigerado. | F56: Media | G56: 00229 | H56: =IF(G56="","",IFERROR(INDEX(Productos!$B:$B,MATCH(G56,Productos!$A:$A,0)),"")) -> Queso campesino | I56: Logística · Vehículo | J56: =IF(F56="Fácil",10,IF(F56="Media",20,30)) -> 20 | K56: Sí
A57: TRV056 | B57: Paletizado y embalaje | C57: Una estiba de «Arroz blanco» se arma con 36 cajas. | D57: Verdadero | E57: Verdadero: una estiba de «Arroz blanco» lleva 36 cajas. | F57: Difícil | G57: 00232 | H57: =IF(G57="","",IFERROR(INDEX(Productos!$B:$B,MATCH(G57,Productos!$A:$A,0)),"")) -> Arroz blanco | I57: Logística · Cajas por estiba | J57: =IF(F57="Fácil",10,IF(F57="Media",20,30)) -> 30 | K57: Sí
A58: TRV057 | B58: Cadena de frío | C58: Para transportar «Uchuva con capacho» (Frescura) se debe mantener una temperatura entre 2 °C y 6 °C. | D58: Verdadero | E58: Verdadero: el rango de transporte de «Uchuva con capacho» es de 2 °C a 6 °C. | F58: Fácil | G58: 00223 | H58: =IF(G58="","",IFERROR(INDEX(Productos!$B:$B,MATCH(G58,Productos!$A:$A,0)),"")) -> Uchuva con capacho | I58: Logística · Temp. transporte mín/máx | J58: =IF(F58="Fácil",10,IF(F58="Media",20,30)) -> 10 | K58: Sí
A59: TRV058 | B59: Vida útil y rotación | C59: La vida útil estimada de «Aguardiente tradicional» es de 1095 días. | D59: Verdadero | E59: Verdadero: la vida útil estimada de «Aguardiente tradicional» es de 1095 días. | F59: Media | G59: 00243 | H59: =IF(G59="","",IFERROR(INDEX(Productos!$B:$B,MATCH(G59,Productos!$A:$A,0)),"")) -> Aguardiente tradicional | I59: Logística · Vida útil (días) | J59: =IF(F59="Fácil",10,IF(F59="Media",20,30)) -> 20 | K59: Sí
A60: TRV059 | B60: Conceptos de logística | C60: La «última milla» es el tramo final de la entrega, desde el último punto de distribución hasta el cliente. | D60: Verdadero | E60: Suele ser el tramo más costoso y complejo de la cadena logística. | F60: Fácil | H60: =IF(G60="","",IFERROR(INDEX(Productos!$B:$B,MATCH(G60,Productos!$A:$A,0)),"")) | I60: Conocimiento general | J60: =IF(F60="Fácil",10,IF(F60="Media",20,30)) -> 10 | K60: Sí
A61: TRV060 | B61: Inventario en tienda | C61: En Surtimax Bucaramanga, «Plátano hartón» tiene un stock por debajo del mínimo y requiere reabastecimiento. | D61: Falso | E61: Falso: el stock (116) está por encima del mínimo (86), estado OK. | F61: Media | G61: 00222 | H61: =IF(G61="","",IFERROR(INDEX(Productos!$B:$B,MATCH(G61,Productos!$A:$A,0)),"")) -> Plátano hartón | I61: Inventario · Estado | J61: =IF(F61="Fácil",10,IF(F61="Media",20,30)) -> 20 | K61: Sí
A62: TRV061 | B62: Origen y producto | C62: «Papas fritas sabor pollo» (Margarita) tiene origen en Antioquia. | D62: Verdadero | E62: Verdadero: el origen de referencia de «Papas fritas sabor pollo» es Antioquia. | F62: Fácil | G62: 00246 | H62: =IF(G62="","",IFERROR(INDEX(Productos!$B:$B,MATCH(G62,Productos!$A:$A,0)),"")) -> Papas fritas sabor pollo | I62: Productos · Origen | J62: =IF(F62="Fácil",10,IF(F62="Media",20,30)) -> 10 | K62: Sí
A63: TRV062 | B63: Cadena de frío | C63: Para transportar «Lulo» (Frescura) se debe mantener una temperatura entre 20 °C y 25 °C. | D63: Falso | E63: Falso: el rango de transporte de «Lulo» es de 7 °C a 10 °C. | F63: Fácil | G63: 00224 | H63: =IF(G63="","",IFERROR(INDEX(Productos!$B:$B,MATCH(G63,Productos!$A:$A,0)),"")) -> Lulo | I63: Logística · Temp. transporte mín/máx | J63: =IF(F63="Fácil",10,IF(F63="Media",20,30)) -> 10 | K63: Sí
A64: TRV063 | B64: Paletizado y embalaje | C64: Una estiba de «Chocolate de mesa» se arma con 60 cajas. | D64: Verdadero | E64: Verdadero: una estiba de «Chocolate de mesa» lleva 60 cajas. | F64: Difícil | G64: 00236 | H64: =IF(G64="","",IFERROR(INDEX(Productos!$B:$B,MATCH(G64,Productos!$A:$A,0)),"")) -> Chocolate de mesa | I64: Logística · Cajas por estiba | J64: =IF(F64="Fácil",10,IF(F64="Media",20,30)) -> 30 | K64: Sí
A65: TRV064 | B65: Transporte y rutas | C65: El vehículo típico para mover «Papa criolla lavada» es: furgón seco. | D65: Verdadero | E65: Verdadero: el vehículo típico para «Papa criolla lavada» es furgón seco. | F65: Media | G65: 00221 | H65: =IF(G65="","",IFERROR(INDEX(Productos!$B:$B,MATCH(G65,Productos!$A:$A,0)),"")) -> Papa criolla lavada | I65: Logística · Vehículo | J65: =IF(F65="Fácil",10,IF(F65="Media",20,30)) -> 20 | K65: Sí
A66: TRV065 | B66: Origen y producto | C66: «Fríjol cargamanto» (Frescura) tiene origen en Antioquia. | D66: Verdadero | E66: Verdadero: el origen de referencia de «Fríjol cargamanto» es Antioquia. | F66: Fácil | G66: 00238 | H66: =IF(G66="","",IFERROR(INDEX(Productos!$B:$B,MATCH(G66,Productos!$A:$A,0)),"")) -> Fríjol cargamanto | I66: Productos · Origen | J66: =IF(F66="Fácil",10,IF(F66="Media",20,30)) -> 10 | K66: Sí
A67: TRV066 | B67: Origen y producto | C67: La conservación recomendada de «Papas fritas sabor pollo» es: congelado -18 °C. | D67: Falso | E67: Falso: la conservación recomendada de «Papas fritas sabor pollo» es lugar fresco y seco. | F67: Fácil | G67: 00246 | H67: =IF(G67="","",IFERROR(INDEX(Productos!$B:$B,MATCH(G67,Productos!$A:$A,0)),"")) -> Papas fritas sabor pollo | I67: Productos · Conservación | J67: =IF(F67="Fácil",10,IF(F67="Media",20,30)) -> 10 | K67: Sí
A68: TRV067 | B68: Origen y producto | C68: La conservación recomendada de «Fríjol cargamanto» es: congelado -18 °C. | D68: Falso | E68: Falso: la conservación recomendada de «Fríjol cargamanto» es lugar fresco y seco. | F68: Fácil | G68: 00238 | H68: =IF(G68="","",IFERROR(INDEX(Productos!$B:$B,MATCH(G68,Productos!$A:$A,0)),"")) -> Fríjol cargamanto | I68: Productos · Conservación | J68: =IF(F68="Fácil",10,IF(F68="Media",20,30)) -> 10 | K68: Sí
A69: TRV068 | B69: Origen y producto | C69: «Mango Tommy» (Frescura) tiene origen en Quindío. | D69: Falso | E69: Falso: el origen de referencia de «Mango Tommy» es Tolima. | F69: Fácil | G69: 00225 | H69: =IF(G69="","",IFERROR(INDEX(Productos!$B:$B,MATCH(G69,Productos!$A:$A,0)),"")) -> Mango Tommy | I69: Productos · Origen | J69: =IF(F69="Fácil",10,IF(F69="Media",20,30)) -> 10 | K69: Sí
A70: TRV069 | B70: Transporte y rutas | C70: «Papel higiénico» se despacha desde Medellín hacia el CD Cali. | D70: Falso | E70: Falso: «Papel higiénico» sale de Medellín hacia el CD Bogotá (~415 km). | F70: Media | G70: 00248 | H70: =IF(G70="","",IFERROR(INDEX(Productos!$B:$B,MATCH(G70,Productos!$A:$A,0)),"")) -> Papel higiénico | I70: Logística · Origen de despacho y CD destino | J70: =IF(F70="Fácil",10,IF(F70="Media",20,30)) -> 20 | K70: Sí
A71: TRV070 | B71: Cadena de frío | C71: «Arequipe» (Alpina) debe transportarse congelado a -18 °C. | D71: Falso | E71: Falso: «Arequipe» se transporta en condiciones secas/ambiente (15–30 °C), sin cadena de frío. | F71: Fácil | G71: 00240 | H71: =IF(G71="","",IFERROR(INDEX(Productos!$B:$B,MATCH(G71,Productos!$A:$A,0)),"")) -> Arequipe | I71: Logística · Transporte con temp. controlada | J71: =IF(F71="Fácil",10,IF(F71="Media",20,30)) -> 10 | K71: Sí
A72: TRV071 | B72: Vida útil y rotación | C72: La vida útil estimada de «Bocadillo veleño» es de 365 días. | D72: Verdadero | E72: Verdadero: la vida útil estimada de «Bocadillo veleño» es de 365 días. | F72: Media | G72: 00239 | H72: =IF(G72="","",IFERROR(INDEX(Productos!$B:$B,MATCH(G72,Productos!$A:$A,0)),"")) -> Bocadillo veleño | I72: Logística · Vida útil (días) | J72: =IF(F72="Fácil",10,IF(F72="Media",20,30)) -> 20 | K72: Sí
... A75: TRV074 | B75: Cadena de frío | C75: «Aceite de girasol» (Gourmet) no necesita transporte con temperatura controlada. | D75: Verdadero | E75: Verdadero: «Aceite de girasol» se transporta en condiciones secas/ambiente (15–30 °C), sin cadena de frío. | F75: Fácil | G75: 00237 | H75: =IF(G75="","",IFERROR(INDEX(Productos!$B:$B,MATCH(G75,Productos!$A:$A,0)),"")) -> Aceite de girasol | I75: Logística · Transporte con temp. controlada | J75: =IF(F75="Fácil",10,IF(F75="Media",20,30)) -> 10 | K75: Sí
A76: TRV075 | B76: Conceptos de logística | C76: La cadena de frío solo importa durante el transporte y se puede ignorar en la bodega. | D76: Falso | E76: La cadena de frío debe mantenerse en producción, bodega, transporte, tienda y exhibición. | F76: Fácil | H76: =IF(G76="","",IFERROR(INDEX(Productos!$B:$B,MATCH(G76,Productos!$A:$A,0)),"")) | I76: Conocimiento general | J76: =IF(F76="Fácil",10,IF(F76="Media",20,30)) -> 10 | K76: Sí
A77: TRV076 | B77: Cadena de frío | C77: «Chocolatina Jet» (Jet) no necesita transporte con temperatura controlada. | D77: Verdadero | E77: Verdadero: «Chocolatina Jet» se transporta en condiciones secas/ambiente (15–25 °C), sin cadena de frío. | F77: Fácil | G77: 00245 | H77: =IF(G77="","",IFERROR(INDEX(Productos!$B:$B,MATCH(G77,Productos!$A:$A,0)),"")) -> Chocolatina Jet | I77: Logística · Transporte con temp. controlada | J77: =IF(F77="Fácil",10,IF(F77="Media",20,30)) -> 10 | K77: Sí
A78: TRV077 | B78: Cadena de frío | C78: Para transportar «Aguacate Hass» (Frescura) se debe mantener una temperatura entre 18 °C y 23 °C. | D78: Falso | E78: Falso: el rango de transporte de «Aguacate Hass» es de 5 °C a 8 °C. | F78: Fácil | G78: 00220 | H78: =IF(G78="","",IFERROR(INDEX(Productos!$B:$B,MATCH(G78,Productos!$A:$A,0)),"")) -> Aguacate Hass | I78: Logística · Temp. transporte mín/máx | J78: =IF(F78="Fácil",10,IF(F78="Media",20,30)) -> 10 | K78: Sí
A79: TRV078 | B79: Cadena de frío | C79: Para transportar «Pulpa de mora congelada» (Frescura) se debe mantener una temperatura entre -22 °C y -18 °C. | D79: Verdadero | E79: Verdadero: el rango de transporte de «Pulpa de mora congelada» es de -22 °C a -18 °C. | F79: Fácil | G79: 00231 | H79: =IF(G79="","",IFERROR(INDEX(Productos!$B:$B,MATCH(G79,Productos!$A:$A,0)),"")) -> Pulpa de mora congelada | I79: Logística · Temp. transporte mín/máx | J79: =IF(F79="Fácil",10,IF(F79="Media",20,30)) -> 10 | K79: Sí
A80: TRV079 | B80: Cadena de frío | C80: «Galletas Saltín» (Noel) no necesita transporte con temperatura controlada. | D80: Verdadero | E80: Verdadero: «Galletas Saltín» se transporta en condiciones secas/ambiente (15–30 °C), sin cadena de frío. | F80: Fácil | G80: 00247 | H80: =IF(G80="","",IFERROR(INDEX(Productos!$B:$B,MATCH(G80,Productos!$A:$A,0)),"")) -> Galletas Saltín | I80: Logística · Transporte con temp. controlada | J80: =IF(F80="Fácil",10,IF(F80="Media",20,30)) -> 10 | K80: Sí
A81: TRV080 | B81: Origen y producto | C81: «Panela cuadrada» (Frescura) tiene origen en Quindío. | D81: Falso | E81: Falso: el origen de referencia de «Panela cuadrada» es Cundinamarca. | F81: Fácil | G81: 00233 | H81: =IF(G81="","",IFERROR(INDEX(Productos!$B:$B,MATCH(G81,Productos!$A:$A,0)),"")) -> Panela cuadrada | I81: Productos · Origen | J81: =IF(F81="Fácil",10,IF(F81="Media",20,30)) -> 10 | K81: Sí
A82: TRV081 | B82: Paletizado y embalaje | C82: Cada caja de «Mango Tommy» contiene 20 unidades. | D82: Falso | E82: Falso: cada caja de «Mango Tommy» trae 10 unidades. | F82: Difícil | G82: 00225 | H82: =IF(G82="","",IFERROR(INDEX(Productos!$B:$B,MATCH(G82,Productos!$A:$A,0)),"")) -> Mango Tommy | I82: Logística · Unidades por caja | J82: =IF(F82="Fácil",10,IF(F82="Media",20,30)) -> 30 | K82: Sí
A83: TRV082 | B83: Paletizado y embalaje | C83: Una estiba de «Café instantáneo clásico» se arma con 210 cajas. | D83: Falso | E83: Falso: una estiba de «Café instantáneo clásico» lleva 140 cajas. | F83: Difícil | G83: 00235 | H83: =IF(G83="","",IFERROR(INDEX(Productos!$B:$B,MATCH(G83,Productos!$A:$A,0)),"")) -> Café instantáneo clásico | I83: Logística · Cajas por estiba | J83: =IF(F83="Fácil",10,IF(F83="Media",20,30)) -> 30 | K83: Sí
A84: TRV083 | B84: Inventario en tienda | C84: Jumbo Bogotá cuenta con cuarto frío en su bodega. | D84: Verdadero | E84: Verdadero: Jumbo Bogotá tiene cuarto frío. | F84: Fácil | H84: =IF(G84="","",IFERROR(INDEX(Productos!$B:$B,MATCH(G84,Productos!$A:$A,0)),"")) | I84: Tiendas · Cuarto frío | J84: =IF(F84="Fácil",10,IF(F84="Media",20,30)) -> 10 | K84: Sí
A85: TRV084 | B85: Paletizado y embalaje | C85: Una estiba de «Bon Bon Bum surtido» se arma con 150 cajas. | D85: Verdadero | E85: Verdadero: una estiba de «Bon Bon Bum surtido» lleva 150 cajas. | F85: Difícil | G85: 00244 | H85: =IF(G85="","",IFERROR(INDEX(Productos!$B:$B,MATCH(G85,Productos!$A:$A,0)),"")) -> Bon Bon Bum surtido | I85: Logística · Cajas por estiba | J85: =IF(F85="Fácil",10,IF(F85="Media",20,30)) -> 30 | K85: Sí
A86: TRV085 | B86: Conceptos de logística | C86: Los productos frágiles, como los de vidrio, se pueden apilar sin límite de niveles en una estiba. | D86: Falso | E86: Los frágiles tienen un máximo de niveles apilables para evitar roturas. | F86: Media | H86: =IF(G86="","",IFERROR(INDEX(Productos!$B:$B,MATCH(G86,Productos!$A:$A,0)),"")) | I86: Conocimiento general | J86: =IF(F86="Fácil",10,IF(F86="Media",20,30)) -> 20 | K86: Sí
A87: TRV086 | B87: Paletizado y embalaje | C87: Cada caja de «Aceite de girasol» contiene 24 unidades. | D87: Falso | E87: Falso: cada caja de «Aceite de girasol» trae 12 unidades. | F87: Difícil | G87: 00237 | H87: =IF(G87="","",IFERROR(INDEX(Productos!$B:$B,MATCH(G87,Productos!$A:$A,0)),"")) -> Aceite de girasol | I87: Logística · Unidades por caja | J87: =IF(F87="Fácil",10,IF(F87="Media",20,30)) -> 30 | K87: Sí
A88: TRV087 | B88: Cadena de frío | C88: «Café instantáneo clásico» (Colcafé) no necesita transporte con temperatura controlada. | D88: Verdadero | E88: Verdadero: «Café instantáneo clásico» se transporta en condiciones secas/ambiente (15–30 °C), sin cadena de frío. | F88: Fácil | G88: 00235 | H88: =IF(G88="","",IFERROR(INDEX(Productos!$B:$B,MATCH(G88,Productos!$A:$A,0)),"")) -> Café instantáneo clásico | I88: Logística · Transporte con temp. controlada | J88: =IF(F88="Fácil",10,IF(F88="Media",20,30)) -> 10 | K88: Sí
A89: TRV088 | B89: Origen y producto | C89: «Bon Bon Bum surtido» (Colombina) tiene origen en Valle del Cauca. | D89: Verdadero | E89: Verdadero: el origen de referencia de «Bon Bon Bum surtido» es Valle del Cauca. | F89: Fácil | G89: 00244 | H89: =IF(G89="","",IFERROR(INDEX(Productos!$B:$B,MATCH(G89,Productos!$A:$A,0)),"")) -> Bon Bon Bum surtido | I89: Productos · Origen | J89: =IF(F89="Fácil",10,IF(F89="Media",20,30)) -> 10 | K89: Sí
A90: TRV089 | B90: Paletizado y embalaje | C90: Una estiba de «Papel higiénico» se arma con 80 cajas. | D90: Verdadero | E90: Verdadero: una estiba de «Papel higiénico» lleva 80 cajas. | F90: Difícil | G90: 00248 | H90: =IF(G90="","",IFERROR(INDEX(Productos!$B:$B,MATCH(G90,Productos!$A:$A,0)),"")) -> Papel higiénico | I90: Logística · Cajas por estiba | J90: =IF(F90="Fácil",10,IF(F90="Media",20,30)) -> 30 | K90: Sí
A91: TRV090 | B91: Inventario en tienda | C91: En Jumbo Bogotá, «Arequipe» tiene un stock por debajo del mínimo y requiere reabastecimiento. | D91: Verdadero | E91: Verdadero: el stock (65) es menor al mínimo (87). | F91: Media | G91: 00240 | H91: =IF(G91="","",IFERROR(INDEX(Productos!$B:$B,MATCH(G91,Productos!$A:$A,0)),"")) -> Arequipe | I91: Inventario · Estado | J91: =IF(F91="Fácil",10,IF(F91="Media",20,30)) -> 20 | K91: Sí
A92: TRV091 | B92: Conceptos de logística | C92: «Picking» es el proceso de recoger productos en la bodega para preparar un pedido. | D92: Verdadero | E92: El picking es la preparación de pedidos tomando los productos de su ubicación. | F92: Fácil | H92: =IF(G92="","",IFERROR(INDEX(Productos!$B:$B,MATCH(G92,Productos!$A:$A,0)),"")) | I92: Conocimiento general | J92: =IF(F92="Fácil",10,IF(F92="Media",20,30)) -> 10 | K92: Sí
A93: TRV092 | B93: Inventario en tienda | C93: Surtimax Bucaramanga se abastece desde el CD Bogotá. | D93: Verdadero | E93: Verdadero: Surtimax Bucaramanga recibe mercancía del CD Bogotá. | F93: Media | H93: =IF(G93="","",IFERROR(INDEX(Productos!$B:$B,MATCH(G93,Productos!$A:$A,0)),"")) | I93: Tiendas · CD que abastece | J93: =IF(F93="Fácil",10,IF(F93="Media",20,30)) -> 20 | K93: Sí
A94: TRV093 | B94: Paletizado y embalaje | C94: Una estiba de «Chocolatina Jet» se arma con 150 cajas. | D94: Falso | E94: Falso: una estiba de «Chocolatina Jet» lleva 100 cajas. | F94: Difícil | G94: 00245 | H94: =IF(G94="","",IFERROR(INDEX(Productos!$B:$B,MATCH(G94,Productos!$A:$A,0)),"")) -> Chocolatina Jet | I94: Logística · Cajas por estiba | J94: =IF(F94="Fácil",10,IF(F94="Media",20,30)) -> 30 | K94: Sí
A95: TRV094 | B95: Cadena de frío | C95: «Chocolate de mesa» (Corona) debe transportarse congelado a -18 °C. | D95: Falso | E95: Falso: «Chocolate de mesa» se transporta en condiciones secas/ambiente (15–25 °C), sin cadena de frío. | F95: Fácil | G95: 00236 | H95: =IF(G95="","",IFERROR(INDEX(Productos!$B:$B,MATCH(G95,Productos!$A:$A,0)),"")) -> Chocolate de mesa | I95: Logística · Transporte con temp. controlada | J95: =IF(F95="Fácil",10,IF(F95="Media",20,30)) -> 10 | K95: Sí
A96: TRV095 | B96: Origen y producto | C96: «Chocolatina Jet» (Jet) tiene origen en Huila. | D96: Falso | E96: Falso: el origen de referencia de «Chocolatina Jet» es Antioquia. | F96: Fácil | G96: 00245 | H96: =IF(G96="","",IFERROR(INDEX(Productos!$B:$B,MATCH(G96,Productos!$A:$A,0)),"")) -> Chocolatina Jet | I96: Productos · Origen | J96: =IF(F96="Fácil",10,IF(F96="Media",20,30)) -> 10 | K96: Sí
A97: TRV096 | B97: Cadena de frío | C97: Para transportar «Banano premium» (Frescura) se debe mantener una temperatura entre 13 °C y 15 °C. | D97: Verdadero | E97: Verdadero: el rango de transporte de «Banano premium» es de 13 °C a 15 °C. | F97: Fácil | G97: 00219 | H97: =IF(G97="","",IFERROR(INDEX(Productos!$B:$B,MATCH(G97,Productos!$A:$A,0)),"")) -> Banano premium | I97: Logística · Temp. transporte mín/máx | J97: =IF(F97="Fácil",10,IF(F97="Media",20,30)) -> 10 | K97: Sí
A98: TRV097 | B98: Transporte y rutas | C98: «Yogurt entero» se despacha desde Sopó hacia el CD Medellín. | D98: Falso | E98: Falso: «Yogurt entero» sale de Sopó hacia el CD Cali (~480 km). | F98: Media | G98: 00228 | H98: =IF(G98="","",IFERROR(INDEX(Productos!$B:$B,MATCH(G98,Productos!$A:$A,0)),"")) -> Yogurt entero | I98: Logística · Origen de despacho y CD destino | J98: =IF(F98="Fácil",10,IF(F98="Media",20,30)) -> 20 | K98: Sí
A99: TRV098 | B99: Paletizado y embalaje | C99: Una estiba de «Gaseosa Colombiana» se arma con 70 cajas. | D99: Verdadero | E99: Verdadero: una estiba de «Gaseosa Colombiana» lleva 70 cajas. | F99: Difícil | G99: 00242 | H99: =IF(G99="","",IFERROR(INDEX(Productos!$B:$B,MATCH(G99,Productos!$A:$A,0)),"")) -> Gaseosa Colombiana | I99: Logística · Cajas por estiba | J99: =IF(F99="Fácil",10,IF(F99="Media",20,30)) -> 30 | K99: Sí
A100: TRV099 | B100: Vida útil y rotación | C100: La vida útil estimada de «Pulpa de mora congelada» es de 365 días. | D100: Verdadero | E100: Verdadero: la vida útil estimada de «Pulpa de mora congelada» es de 365 días. | F100: Media | G100: 00231 | H100: =IF(G100="","",IFERROR(INDEX(Productos!$B:$B,MATCH(G100,Productos!$A:$A,0)),"")) -> Pulpa de mora congelada | I100: Logística · Vida útil (días) | J100: =IF(F100="Fácil",10,IF(F100="Media",20,30)) -> 20 | K100: Sí
A101: TRV100 | B101: Conceptos de logística | C101: Un centro de distribución recibe mercancía de varios proveedores y la despacha a las tiendas. | D101: Verdadero | E101: Consolida pedidos y optimiza el transporte hacia los puntos de venta. | F101: Fácil | H101: =IF(G101="","",IFERROR(INDEX(Productos!$B:$B,MATCH(G101,Productos!$A:$A,0)),"")) | I101: Conocimiento general | J101: =IF(F101="Fácil",10,IF(F101="Media",20,30)) -> 10 | K101: Sí
A102: TRV101 | B102: Inventario en tienda | C102: En Éxito Cartagena, «Leche entera pasteurizada» tiene un stock por debajo del mínimo y requiere reabastecimiento. | D102: Verdadero | E102: Verdadero: el stock (29) es menor al mínimo (42). | F102: Media | G102: 00227 | H102: =IF(G102="","",IFERROR(INDEX(Productos!$B:$B,MATCH(G102,Productos!$A:$A,0)),"")) -> Leche entera pasteurizada | I102: Inventario · Estado | J102: =IF(F102="Fácil",10,IF(F102="Media",20,30)) -> 20 | K102: Sí
...
